Metadata-Version: 1.1
Name: venn
Version: 0.1
Summary: Venn diagrams for 2, 3, 4, 5, 6 sets
Home-page: https://github.com/LankyCyril/pyvenn
Author: Kirill Grigorev
Author-email: UNKNOWN
License: GPLv3
Platform: UNKNOWN
Classifier: Development Status :: 3 - Alpha
Classifier: Programming Language :: Python :: 3
Classifier: Environment :: Console
Classifier: License :: OSI Approved :: GNU General Public License v3 (GPLv3)
Classifier: Intended Audience :: Science/Research
Classifier: Topic :: Scientific/Engineering :: Visualization
